{
  "DLSVersion": "2.1.6",
  "Name": "8-BIT ADDER",
  "NameLocation": 0,
  "ChipType": 0,
  "Size": {
    "x": 1.025,
    "y": 4.25
  },
  "Colour": {
    "r": 0.157412291,
    "g": 0.741890848,
    "b": 0.226179823,
    "a": 1
  },
  "InputPins":[
    {
      "Name":"A0",
      "ID":824038861,
      "Position":{
        "x":-12.0,
        "y":5.625
      },
      "BitCount":1,
      "Colour":0,
      "ValueDisplayMode":0
    },
    {
      "Name":"B0",
      "ID":2080051169,
      "Position":{
        "x":-12.0,
        "y":5.125
      },
      "BitCount":1,
      "Colour":0,
      "ValueDisplayMode":0
    },
    {
      "Name":"A1",
      "ID":164096582,
      "Position":{
        "x":-12.0,
        "y":4.625
      },
      "BitCount":1,
      "Colour":0,
      "ValueDisplayMode":0
    },
    {
      "Name":"B1",
      "ID":764158035,
      "Position":{
        "x":-12.0,
        "y":4.125
      },
      "BitCount":1,
      "Colour":0,
      "ValueDisplayMode":0
    },
    {
      "Name":"A2",
      "ID":1301758237,
      "Position":{
        "x":-12.0,
        "y":3.625
      },
      "BitCount":1,
      "Colour":0,
      "ValueDisplayMode":0
    },
    {
      "Name":"B2",
      "ID":660055317,
      "Position":{
        "x":-12.0,
        "y":3.125
      },
      "BitCount":1,
      "Colour":0,
      "ValueDisplayMode":0
    },
    {
      "Name":"A3",
      "ID":698781440,
      "Position":{
        "x":-12.0,
        "y":2.625
      },
      "BitCount":1,
      "Colour":0,
      "ValueDisplayMode":0
    },
    {
      "Name":"B3",
      "ID":1946578072,
      "Position":{
        "x":-12.0,
        "y":2.125
      },
      "BitCount":1,
      "Colour":0,
      "ValueDisplayMode":0
    },
    {
      "Name":"CIN",
      "ID":1830512408,
      "Position":{
        "x":-12.0,
        "y":1.25
      },
      "BitCount":1,
      "Colour":0,
      "ValueDisplayMode":0
    },
    {
      "Name":"A4",
      "ID":732326024,
      "Position":{
        "x":-12.0,
        "y":0.5
      },
      "BitCount":1,
      "Colour":0,
      "ValueDisplayMode":0
    },
    {
      "Name":"B4",
      "ID":1633675255,
      "Position":{
        "x":-12.0,
        "y":0.0
      },
      "BitCount":1,
      "Colour":0,
      "ValueDisplayMode":0
    },
    {
      "Name":"A5",
      "ID":1363838798,
      "Position":{
        "x":-12.0,
        "y":-0.5
      },
      "BitCount":1,
      "Colour":0,
      "ValueDisplayMode":0
    },
    {
      "Name":"B5",
      "ID":891078430,
      "Position":{
        "x":-12.0,
        "y":-1.0
      },
      "BitCount":1,
      "Colour":0,
      "ValueDisplayMode":0
    },
    {
      "Name":"A6",
      "ID":1721846934,
      "Position":{
        "x":-12.0,
        "y":-1.5
      },
      "BitCount":1,
      "Colour":0,
      "ValueDisplayMode":0
    },
    {
      "Name":"B6",
      "ID":1103928779,
      "Position":{
        "x":-12.0,
        "y":-2.0
      },
      "BitCount":1,
      "Colour":0,
      "ValueDisplayMode":0
    },
    {
      "Name":"A7",
      "ID":1688940949,
      "Position":{
        "x":-12.0,
        "y":-2.5
      },
      "BitCount":1,
      "Colour":0,
      "ValueDisplayMode":0
    },
    {
      "Name":"B7",
      "ID":1119163715,
      "Position":{
        "x":-12.0,
        "y":-3.0
      },
      "BitCount":1,
      "Colour":0,
      "ValueDisplayMode":0
    }
  ],
  "OutputPins":[
    {
      "Name":"SUM1",
      "ID":677932090,
      "Position":{
        "x":-3.375,
        "y":4.25
      },
      "BitCount":1,
      "Colour":0,
      "ValueDisplayMode":0
    },
    {
      "Name":"SUM2",
      "ID":314382046,
      "Position":{
        "x":-3.375,
        "y":3.5
      },
      "BitCount":1,
      "Colour":0,
      "ValueDisplayMode":0
    },
    {
      "Name":"SUM3",
      "ID":1420186295,
      "Position":{
        "x":-3.375,
        "y":2.75
      },
      "BitCount":1,
      "Colour":0,
      "ValueDisplayMode":0
    },
    {
      "Name":"SUM4",
      "ID":852565216,
      "Position":{
        "x":-3.375,
        "y":2.0
      },
      "BitCount":1,
      "Colour":0,
      "ValueDisplayMode":0
    },
    {
      "Name":"SUM5",
      "ID":1104063500,
      "Position":{
        "x":-3.375,
        "y":1.25
      },
      "BitCount":1,
      "Colour":0,
      "ValueDisplayMode":0
    },
    {
      "Name":"SUM6",
      "ID":614961156,
      "Position":{
        "x":-3.375,
        "y":0.5
      },
      "BitCount":1,
      "Colour":0,
      "ValueDisplayMode":0
    },
    {
      "Name":"SUM7",
      "ID":1035269896,
      "Position":{
        "x":-3.375,
        "y":-0.25
      },
      "BitCount":1,
      "Colour":0,
      "ValueDisplayMode":0
    },
    {
      "Name":"SUM8",
      "ID":1908078215,
      "Position":{
        "x":-3.375,
        "y":-1.0
      },
      "BitCount":1,
      "Colour":0,
      "ValueDisplayMode":0
    },
    {
      "Name":"CARRY OUT",
      "ID":1562450395,
      "Position":{
        "x":-3.375,
        "y":-1.5
      },
      "BitCount":1,
      "Colour":0,
      "ValueDisplayMode":0
    }
  ],
  "SubChips":[
    {
      "Name":"4-BIT ADDER",
      "ID":75179430,
      "Label":"",
      "Position":{
        "x":-7.4775,
        "y":2.75
      },
      "OutputPinColourInfo":[{"PinColour":0,"PinID":1263763842},{"PinColour":0,"PinID":1676829058},{"PinColour":0,"PinID":627837009},{"PinColour":0,"PinID":647438487},{"PinColour":0,"PinID":1580294555}],
      "InternalData":null
    },
    {
      "Name":"4-BIT ADDER",
      "ID":1162061905,
      "Label":"",
      "Position":{
        "x":-7.4775,
        "y":-0.5
      },
      "OutputPinColourInfo":[{"PinColour":0,"PinID":1263763842},{"PinColour":0,"PinID":1676829058},{"PinColour":0,"PinID":627837009},{"PinColour":0,"PinID":647438487},{"PinColour":0,"PinID":1580294555}],
      "InternalData":null
    }
  ],
  "Wires":[
    {
      "SourcePinAddress":{
        "PinID":0,
        "PinOwnerID":1830512408
      },
      "TargetPinAddress":{
        "PinID":1923125660,
        "PinOwnerID":75179430
      },
      "ConnectionType":0,
      "ConnectedWireIndex":-1,
      "ConnectedWireSegmentIndex":-1,
      "Points":[{"x":0.0,"y":0.0},{"x":-8.875,"y":1.25},{"x":-8.875,"y":2.75},{"x":0.0,"y":0.0}]
    },
    {
      "SourcePinAddress":{
        "PinID":0,
        "PinOwnerID":824038861
      },
      "TargetPinAddress":{
        "PinID":945376942,
        "PinOwnerID":75179430
      },
      "ConnectionType":0,
      "ConnectedWireIndex":-1,
      "ConnectedWireSegmentIndex":-1,
      "Points":[{"x":0.0,"y":0.0},{"x":-9.375,"y":5.625},{"x":-9.375,"y":3.75},{"x":0.0,"y":0.0}]
    },
    {
      "SourcePinAddress":{
        "PinID":0,
        "PinOwnerID":2080051169
      },
      "TargetPinAddress":{
        "PinID":1002386122,
        "PinOwnerID":75179430
      },
      "ConnectionType":0,
      "ConnectedWireIndex":-1,
      "ConnectedWireSegmentIndex":-1,
      "Points":[{"x":0.0,"y":0.0},{"x":-9.5,"y":5.125},{"x":-9.5,"y":3.5},{"x":0.0,"y":0.0}]
    },
    {
      "SourcePinAddress":{
        "PinID":0,
        "PinOwnerID":164096582
      },
      "TargetPinAddress":{
        "PinID":1635198830,
        "PinOwnerID":75179430
      },
      "ConnectionType":0,
      "ConnectedWireIndex":-1,
      "ConnectedWireSegmentIndex":-1,
      "Points":[{"x":0.0,"y":0.0},{"x":-9.6875,"y":4.625},{"x":-9.625,"y":4.625},{"x":-9.625,"y":3.25},{"x":0.0,"y":0.0}]
    },
    {
      "SourcePinAddress":{
        "PinID":0,
        "PinOwnerID":764158035
      },
      "TargetPinAddress":{
        "PinID":575579904,
        "PinOwnerID":75179430
      },
      "ConnectionType":0,
      "ConnectedWireIndex":-1,
      "ConnectedWireSegmentIndex":-1,
      "Points":[{"x":0.0,"y":0.0},{"x":-9.75,"y":4.125},{"x":-9.75,"y":3.0},{"x":0.0,"y":0.0}]
    },
    {
      "SourcePinAddress":{
        "PinID":0,
        "PinOwnerID":1301758237
      },
      "TargetPinAddress":{
        "PinID":323900794,
        "PinOwnerID":75179430
      },
      "ConnectionType":0,
      "ConnectedWireIndex":-1,
      "ConnectedWireSegmentIndex":-1,
      "Points":[{"x":0.0,"y":0.0},{"x":-9.875,"y":3.625},{"x":-9.875,"y":2.5},{"x":0.0,"y":0.0}]
    },
    {
      "SourcePinAddress":{
        "PinID":0,
        "PinOwnerID":660055317
      },
      "TargetPinAddress":{
        "PinID":878685570,
        "PinOwnerID":75179430
      },
      "ConnectionType":0,
      "ConnectedWireIndex":-1,
      "ConnectedWireSegmentIndex":-1,
      "Points":[{"x":0.0,"y":0.0},{"x":-10.0,"y":3.125},{"x":-10.0,"y":2.25},{"x":0.0,"y":0.0}]
    },
    {
      "SourcePinAddress":{
        "PinID":0,
        "PinOwnerID":698781440
      },
      "TargetPinAddress":{
        "PinID":1481247833,
        "PinOwnerID":75179430
      },
      "ConnectionType":0,
      "ConnectedWireIndex":-1,
      "ConnectedWireSegmentIndex":-1,
      "Points":[{"x":0.0,"y":0.0},{"x":-10.125,"y":2.625},{"x":-10.125,"y":2.0},{"x":0.0,"y":0.0}]
    },
    {
      "SourcePinAddress":{
        "PinID":0,
        "PinOwnerID":1946578072
      },
      "TargetPinAddress":{
        "PinID":166595740,
        "PinOwnerID":75179430
      },
      "ConnectionType":0,
      "ConnectedWireIndex":-1,
      "ConnectedWireSegmentIndex":-1,
      "Points":[{"x":0.0,"y":0.0},{"x":-10.3125,"y":2.125},{"x":-10.25,"y":2.125},{"x":-10.25,"y":1.75},{"x":0.0,"y":0.0}]
    },
    {
      "SourcePinAddress":{
        "PinID":1580294555,
        "PinOwnerID":75179430
      },
      "TargetPinAddress":{
        "PinID":1923125660,
        "PinOwnerID":1162061905
      },
      "ConnectionType":0,
      "ConnectedWireIndex":-1,
      "ConnectedWireSegmentIndex":-1,
      "Points":[{"x":0.0,"y":0.0},{"x":-6.625,"y":1.75},{"x":-6.625,"y":1.25},{"x":-8.625,"y":1.25},{"x":-8.625,"y":-0.5},{"x":0.0,"y":0.0}]
    },
    {
      "SourcePinAddress":{
        "PinID":0,
        "PinOwnerID":732326024
      },
      "TargetPinAddress":{
        "PinID":945376942,
        "PinOwnerID":1162061905
      },
      "ConnectionType":0,
      "ConnectedWireIndex":-1,
      "ConnectedWireSegmentIndex":-1,
      "Points":[{"x":0.0,"y":0.0},{"x":0.0,"y":0.0}]
    },
    {
      "SourcePinAddress":{
        "PinID":0,
        "PinOwnerID":1633675255
      },
      "TargetPinAddress":{
        "PinID":1002386122,
        "PinOwnerID":1162061905
      },
      "ConnectionType":0,
      "ConnectedWireIndex":-1,
      "ConnectedWireSegmentIndex":-1,
      "Points":[{"x":0.0,"y":0.0},{"x":-11.0,"y":0.0},{"x":-11.0,"y":0.25},{"x":0.0,"y":0.0}]
    },
    {
      "SourcePinAddress":{
        "PinID":0,
        "PinOwnerID":1363838798
      },
      "TargetPinAddress":{
        "PinID":1635198830,
        "PinOwnerID":1162061905
      },
      "ConnectionType":0,
      "ConnectedWireIndex":-1,
      "ConnectedWireSegmentIndex":-1,
      "Points":[{"x":0.0,"y":0.0},{"x":-10.875,"y":-0.5},{"x":-10.875,"y":-0.125},{"x":-10.875,"y":0.0},{"x":0.0,"y":0.0}]
    },
    {
      "SourcePinAddress":{
        "PinID":0,
        "PinOwnerID":891078430
      },
      "TargetPinAddress":{
        "PinID":575579904,
        "PinOwnerID":1162061905
      },
      "ConnectionType":0,
      "ConnectedWireIndex":-1,
      "ConnectedWireSegmentIndex":-1,
      "Points":[{"x":0.0,"y":0.0},{"x":-10.75,"y":-1.0},{"x":-10.75,"y":-0.25},{"x":0.0,"y":0.0}]
    },
    {
      "SourcePinAddress":{
        "PinID":0,
        "PinOwnerID":1721846934
      },
      "TargetPinAddress":{
        "PinID":323900794,
        "PinOwnerID":1162061905
      },
      "ConnectionType":0,
      "ConnectedWireIndex":-1,
      "ConnectedWireSegmentIndex":-1,
      "Points":[{"x":0.0,"y":0.0},{"x":-10.625,"y":-1.5},{"x":-10.625,"y":-0.75},{"x":0.0,"y":0.0}]
    },
    {
      "SourcePinAddress":{
        "PinID":0,
        "PinOwnerID":1103928779
      },
      "TargetPinAddress":{
        "PinID":878685570,
        "PinOwnerID":1162061905
      },
      "ConnectionType":0,
      "ConnectedWireIndex":-1,
      "ConnectedWireSegmentIndex":-1,
      "Points":[{"x":0.0,"y":0.0},{"x":-10.5,"y":-2.0},{"x":-10.5,"y":-1.0},{"x":0.0,"y":0.0}]
    },
    {
      "SourcePinAddress":{
        "PinID":0,
        "PinOwnerID":1688940949
      },
      "TargetPinAddress":{
        "PinID":1481247833,
        "PinOwnerID":1162061905
      },
      "ConnectionType":0,
      "ConnectedWireIndex":-1,
      "ConnectedWireSegmentIndex":-1,
      "Points":[{"x":0.0,"y":0.0},{"x":-10.375,"y":-2.5},{"x":-10.375,"y":-1.25},{"x":0.0,"y":0.0}]
    },
    {
      "SourcePinAddress":{
        "PinID":0,
        "PinOwnerID":1119163715
      },
      "TargetPinAddress":{
        "PinID":166595740,
        "PinOwnerID":1162061905
      },
      "ConnectionType":0,
      "ConnectedWireIndex":-1,
      "ConnectedWireSegmentIndex":-1,
      "Points":[{"x":0.0,"y":0.0},{"x":-10.25,"y":-3.0},{"x":-10.25,"y":-1.5},{"x":0.0,"y":0.0}]
    },
    {
      "SourcePinAddress":{
        "PinID":1580294555,
        "PinOwnerID":1162061905
      },
      "TargetPinAddress":{
        "PinID":0,
        "PinOwnerID":1562450395
      },
      "ConnectionType":0,
      "ConnectedWireIndex":-1,
      "ConnectedWireSegmentIndex":-1,
      "Points":[{"x":0.0,"y":0.0},{"x":0.0,"y":0.0}]
    },
    {
      "SourcePinAddress":{
        "PinID":1263763842,
        "PinOwnerID":75179430
      },
      "TargetPinAddress":{
        "PinID":0,
        "PinOwnerID":677932090
      },
      "ConnectionType":0,
      "ConnectedWireIndex":-1,
      "ConnectedWireSegmentIndex":-1,
      "Points":[{"x":0.0,"y":0.0},{"x":-5.0,"y":3.75},{"x":-5.0,"y":4.25},{"x":0.0,"y":0.0}]
    },
    {
      "SourcePinAddress":{
        "PinID":1676829058,
        "PinOwnerID":75179430
      },
      "TargetPinAddress":{
        "PinID":0,
        "PinOwnerID":314382046
      },
      "ConnectionType":0,
      "ConnectedWireIndex":-1,
      "ConnectedWireSegmentIndex":-1,
      "Points":[{"x":0.0,"y":0.0},{"x":-5.0,"y":3.25},{"x":-5.0,"y":3.5},{"x":0.0,"y":0.0}]
    },
    {
      "SourcePinAddress":{
        "PinID":627837009,
        "PinOwnerID":75179430
      },
      "TargetPinAddress":{
        "PinID":0,
        "PinOwnerID":1420186295
      },
      "ConnectionType":0,
      "ConnectedWireIndex":-1,
      "ConnectedWireSegmentIndex":-1,
      "Points":[{"x":0.0,"y":0.0},{"x":0.0,"y":0.0}]
    },
    {
      "SourcePinAddress":{
        "PinID":647438487,
        "PinOwnerID":75179430
      },
      "TargetPinAddress":{
        "PinID":0,
        "PinOwnerID":852565216
      },
      "ConnectionType":0,
      "ConnectedWireIndex":-1,
      "ConnectedWireSegmentIndex":-1,
      "Points":[{"x":0.0,"y":0.0},{"x":-5.0,"y":2.25},{"x":-5.0,"y":2.0},{"x":0.0,"y":0.0}]
    },
    {
      "SourcePinAddress":{
        "PinID":1263763842,
        "PinOwnerID":1162061905
      },
      "TargetPinAddress":{
        "PinID":0,
        "PinOwnerID":1104063500
      },
      "ConnectionType":0,
      "ConnectedWireIndex":-1,
      "ConnectedWireSegmentIndex":-1,
      "Points":[{"x":0.0,"y":0.0},{"x":-6.125,"y":0.5},{"x":-6.125,"y":1.25},{"x":0.0,"y":0.0}]
    },
    {
      "SourcePinAddress":{
        "PinID":1676829058,
        "PinOwnerID":1162061905
      },
      "TargetPinAddress":{
        "PinID":0,
        "PinOwnerID":614961156
      },
      "ConnectionType":0,
      "ConnectedWireIndex":-1,
      "ConnectedWireSegmentIndex":-1,
      "Points":[{"x":0.0,"y":0.0},{"x":-6.0,"y":0.0},{"x":-6.0,"y":0.5},{"x":0.0,"y":0.0}]
    },
    {
      "SourcePinAddress":{
        "PinID":627837009,
        "PinOwnerID":1162061905
      },
      "TargetPinAddress":{
        "PinID":0,
        "PinOwnerID":1035269896
      },
      "ConnectionType":0,
      "ConnectedWireIndex":-1,
      "ConnectedWireSegmentIndex":-1,
      "Points":[{"x":0.0,"y":0.0},{"x":-5.875,"y":-0.5},{"x":-5.875,"y":-0.25},{"x":0.0,"y":0.0}]
    },
    {
      "SourcePinAddress":{
        "PinID":647438487,
        "PinOwnerID":1162061905
      },
      "TargetPinAddress":{
        "PinID":0,
        "PinOwnerID":1908078215
      },
      "ConnectionType":0,
      "ConnectedWireIndex":-1,
      "ConnectedWireSegmentIndex":-1,
      "Points":[{"x":0.0,"y":0.0},{"x":0.0,"y":0.0}]
    }
  ],
  "Displays": null
}